run_clang_format.py
run_clang_format-1.2.0.dist-info/licenses/LICENSE
run_clang_format-1.2.0.dist-info/METADATA
run_clang_format-1.2.0.dist-info/WHEEL
run_clang_format-1.2.0.dist-info/entry_points.txt
run_clang_format-1.2.0.dist-info/top_level.txt
run_clang_format-1.2.0.dist-info/RECORD
